rgame/__init__.py
rgame/rgame.py
rgame/RGame/Physics.dll
rgame/RGame/RGamePic.png
rgame/RGame/Time.dll
rgame-1.4.24.dist-info/LICENSE.txt
rgame-1.4.24.dist-info/METADATA
rgame-1.4.24.dist-info/WHEEL
rgame-1.4.24.dist-info/top_level.txt
rgame-1.4.24.dist-info/RECORD
