Metadata-Version: 2.1
Name: rgame
Version: 1.4.24
Summary: A python game engine/graphics library
Author-email: Gyula Rabai <gyula.rabai@ipswich.school>
License: GNU GPLv3
Project-URL: Homepage, https://gyularabai.wixsite.com/ipswich-school-game
Classifier: Development Status :: 3 - Alpha
Classifier: Programming Language :: Python :: 3
Classifier: License :: OSI Approved :: GNU General Public License v3 (GPLv3)
Classifier: Operating System :: Microsoft :: Windows :: Windows 10
Requires-Python: >=3.10
License-File: LICENSE.txt
